py0/__init__.py
py0/main.py
py0/transpiler.py
py0/generated/Py0Lexer.py
py0/generated/Py0Listener.py
py0/generated/Py0Parser.py
py0/generated/Py0Visitor.py
py0/generated/__init__.py
py0ltv-0.1.6.dist-info/LICENSE
py0ltv-0.1.6.dist-info/METADATA
py0ltv-0.1.6.dist-info/WHEEL
py0ltv-0.1.6.dist-info/entry_points.txt
py0ltv-0.1.6.dist-info/top_level.txt
py0ltv-0.1.6.dist-info/RECORD
