Metadata-Version: 2.1
Name: py0ltv
Version: 0.1.6
Summary: A transpiler for .py0 files to Python
Author-email: LapTrinhVui <syriackeyboard@gmail.com>
Classifier: Programming Language :: Python :: 3
Classifier: License :: OSI Approved :: MIT License
Classifier: Operating System :: OS Independent
Requires-Python: >=3.6
License-File: LICENSE
Requires-Dist: antlr4-python3-runtime
